<annotation>
	<folder>017_top_grass</folder>
	<filename>017_top_grass00226.jpg</filename>
	<path>/Users/sebastian/Projects/RumexClassification/VideosSplitIntoFrames/017_top_grass/017_top_grass00226.jpg</path>
	<source>
		<database>Unknown</database>
	</source>
	<size>
		<width>1280</width>
		<height>720</height>
		<depth>3</depth>
	</size>
	<segmented>0</segmented>
	<object>
		<name>rumex</name>
		<pose>Unspecified</pose>
		<truncated>0</truncated>
		<difficult>0</difficult>
		<bndbox>
			<xmin>738</xmin>
			<ymin>436</ymin>
			<xmax>813</xmax>
			<ymax>495</ymax>
		</bndbox>
	</object>
	<object>
		<name>rumex</name>
		<pose>Unspecified</pose>
		<truncated>0</truncated>
		<difficult>0</difficult>
		<bndbox>
			<xmin>485</xmin>
			<ymin>414</ymin>
			<xmax>640</xmax>
			<ymax>495</ymax>
		</bndbox>
	</object>
</annotation>
