<annotation>
	<folder>028_top_snow</folder>
	<filename>028_00111.jpg</filename>
	<path>/Users/jacobhertz/Studie/Kurser/X-tech/X-tech - 10. semester/Project/VideoAndImages/RumexVideo/VideosSplitIntoFrames/028_top_snow/028_00111.jpg</path>
	<source>
		<database>Unknown</database>
	</source>
	<size>
		<width>1280</width>
		<height>720</height>
		<depth>3</depth>
	</size>
	<segmented>0</segmented>
	<object>
		<name>rumex</name>
		<pose>Unspecified</pose>
		<truncated>0</truncated>
		<difficult>0</difficult>
		<bndbox>
			<xmin>488</xmin>
			<ymin>172</ymin>
			<xmax>847</xmax>
			<ymax>469</ymax>
		</bndbox>
	</object>
	<object>
		<name>root</name>
		<pose>Unspecified</pose>
		<truncated>0</truncated>
		<difficult>0</difficult>
		<bndbox>
			<xmin>601</xmin>
			<ymin>324</ymin>
			<xmax>693</xmax>
			<ymax>400</ymax>
		</bndbox>
	</object>
</annotation>
